pylibhack.py
pylibhack-1.0.0.dist-info/LICENSE
pylibhack-1.0.0.dist-info/METADATA
pylibhack-1.0.0.dist-info/WHEEL
pylibhack-1.0.0.dist-info/RECORD
