Metadata-Version: 2.1
Name: pylibhack
Version: 1.0.0
Summary: Чтобы узнать функции вызовите в коде pylibhack.help()
License: MIT
Author: s3al4er
Requires-Python: >=3.10,<4.0
Classifier: License :: OSI Approved :: MIT License
Classifier: Programming Language :: Python :: 3
Classifier: Programming Language :: Python :: 3.10
Classifier: Programming Language :: Python :: 3.11
Classifier: Programming Language :: Python :: 3.12
